simtext/__init__.py
simtext/computetext.py
simtext-1.2.dist-info/LICENSE
simtext-1.2.dist-info/METADATA
simtext-1.2.dist-info/WHEEL
simtext-1.2.dist-info/top_level.txt
simtext-1.2.dist-info/RECORD
