Metadata-Version: 2.1
Name: simtext
Version: 1.2
Summary: 文本、文档相似性计算
Home-page: https://github.com/hidadeng/simtext
Author: 大邓
Author-email: thunderhit@qq.com
License: MIT
Keywords: text similarity,文本相似性,text mining,文本挖掘
Platform: UNKNOWN
Requires-Python: >=3.5
Requires-Dist: scikit-learn
Requires-Dist: jieba
